umnet_pyncs/__init__.py
umnet_pyncs/state/__init__.py
umnet_pyncs/state/models/__init__.py
umnet_pyncs/state/models/base.py
umnet_pyncs/state/models/ios.py
umnet_pyncs/state/models/junos.py
umnet_pyncs/state/models/nxos.py
umnet_pyncs/state/models/utils.py
umnet_pyncs/state/state_manager.py
umnet_pyncs/state/templates/cisco_ios_show_lldp_neighbors_detail.textfsm
umnet_pyncs/state/templates/cisco_nxos_show_bgp_l2vpn_evpn_macip.textfsm
umnet_pyncs/state/templates/cisco_nxos_show_ip_arp_detail_vrf_all.textfsm
umnet_pyncs/utils.py
umnet_pyncs-0.1.44.dist-info/METADATA
umnet_pyncs-0.1.44.dist-info/WHEEL
umnet_pyncs-0.1.44.dist-info/RECORD
