Metadata-Version: 2.3
Name: umnet-pyncs
Version: 0.1.44
Summary: custom python module for NCS helpers
Author: Nick Grundler
Author-email: grundler@umich.edu
Requires-Python: >=3.7,<4.0
Classifier: Programming Language :: Python :: 3
Classifier: Programming Language :: Python :: 3.7
Classifier: Programming Language :: Python :: 3.8
Classifier: Programming Language :: Python :: 3.9
Classifier: Programming Language :: Python :: 3.10
Classifier: Programming Language :: Python :: 3.11
Classifier: Programming Language :: Python :: 3.12
Classifier: Programming Language :: Python :: 3.13
Requires-Dist: importlib-metadata (==6.0.0) ; python_version < "3.8"
Requires-Dist: multiprocessing-logging (>=0.3.3,<0.4.0)
Requires-Dist: netaddr (>=0.8.0,<0.9.0)
Requires-Dist: ntc-templates (>=3.0.0,<4.0.0)
